{"cameraMode":{"drawMode":0,"name":"Shaded","section":"Shading Mode"},"sceneLighting":true,"audioPlay":false,"sceneViewState":{"m_AlwaysRefresh":false,"showFog":true,"showSkybox":true,"showFlares":true,"showImageEffects":true,"showParticleSystems":true,"showVisualEffectGraphs":true,"m_FxEnabled":true},"in2DMode":false,"pivot":{"x":1.6033884286880494,"y":-9.207948684692383,"z":61.70140838623047},"rotation":{"x":-0.30106016993522646,"y":0.5974303483963013,"z":-0.25803691148757937,"w":-0.6970418095588684},"size":32.94392013549805,"orthographic":false}